MarineSystemSim/__init__.py
MarineSystemSim-0.1.dist-info/DESCRIPTION.rst
MarineSystemSim-0.1.dist-info/METADATA
MarineSystemSim-0.1.dist-info/RECORD
MarineSystemSim-0.1.dist-info/WHEEL
MarineSystemSim-0.1.dist-info/metadata.json
MarineSystemSim-0.1.dist-info/top_level.txt
